.git/logs/HEAD
.venv/lib/python3.11/site-packages/client/keys/new.key
.venv/lib/python3.11/site-packages/client/keys/one.key
.venv/lib/python3.11/site-packages/client/keys/two.key
pyqtchat8741/__init__.py
pyqtchat8741/client/__init__.py
pyqtchat8741/client/cli/__init__.py
pyqtchat8741/client/client.py
pyqtchat8741/client/core/__init__.py
pyqtchat8741/client/core/core.py
pyqtchat8741/client/core/decos.py
pyqtchat8741/client/core/descriptors.py
pyqtchat8741/client/core/errors_user.py
pyqtchat8741/client/core/metaclasses.py
pyqtchat8741/client/core/utils.py
pyqtchat8741/client/core/variables.py
pyqtchat8741/client/db_client/__init__.py
pyqtchat8741/client/db_client/database.py
pyqtchat8741/client/db_client/models.py
pyqtchat8741/client/db_client/storage.py
pyqtchat8741/client/gui/__init__.py
pyqtchat8741/client/gui/add_contact.py
pyqtchat8741/client/gui/client.ui
pyqtchat8741/client/gui/del_contact.py
pyqtchat8741/client/gui/main_window.py
pyqtchat8741/client/gui/main_window_conv.py
pyqtchat8741/client/gui/start_dialog.py
pyqtchat8741/client/keys/new.key
pyqtchat8741/client/keys/one.key
pyqtchat8741/client/keys/two.key
pyqtchat8741/client/logs/__init__.py
pyqtchat8741/client/logs/client.log
pyqtchat8741/client/logs/logger.py
pyqtchat8741/launcher.py
pyqtchat8741/launcher_macos.py
pyqtchat8741/launcher_ubuntu.py
pyqtchat8741/server/__init__.py
pyqtchat8741/server/cli/__init__.py
pyqtchat8741/server/core/__init__.py
pyqtchat8741/server/core/core.py
pyqtchat8741/server/core/decos.py
pyqtchat8741/server/core/errors_user.py
pyqtchat8741/server/core/metaclasses.py
pyqtchat8741/server/core/utils.py
pyqtchat8741/server/core/variables.py
pyqtchat8741/server/db_server/__init__.py
pyqtchat8741/server/db_server/database.py
pyqtchat8741/server/db_server/models.py
pyqtchat8741/server/db_server/storage.py
pyqtchat8741/server/gui/__init__.py
pyqtchat8741/server/gui/add_user.py
pyqtchat8741/server/gui/config_window.py
pyqtchat8741/server/gui/main_window.py
pyqtchat8741-0.1.18.dist-info/METADATA
pyqtchat8741-0.1.18.dist-info/WHEEL
pyqtchat8741-0.1.18.dist-info/entry_points.txt
pyqtchat8741-0.1.18.dist-info/RECORD
